.gitignore
PKG-INFO
demo.py
pyproject.toml
bec_ipython_client/__init__.py
bec_ipython_client/beamline_mixin.py
bec_ipython_client/bec_magics.py
bec_ipython_client/bec_startup.py
bec_ipython_client/main.py
bec_ipython_client/prettytable.py
bec_ipython_client/progressbar.py
bec_ipython_client/signals.py
bec_ipython_client/callbacks/__init__.py
bec_ipython_client/callbacks/device_progress.py
bec_ipython_client/callbacks/ipython_live_updates.py
bec_ipython_client/callbacks/live_table.py
bec_ipython_client/callbacks/move_device.py
bec_ipython_client/callbacks/utils.py
bec_ipython_client/high_level_interfaces/__init__.py
bec_ipython_client/high_level_interfaces/bec_hli.py
bec_ipython_client/high_level_interfaces/spec_hli.py
bec_ipython_client/plugins/__init__.py
bec_ipython_client/plugins/SLS/__init__.py
bec_ipython_client/plugins/SLS/sls_info.py
bec_ipython_client/plugins/XTreme/__init__.py
bec_ipython_client/plugins/XTreme/x-treme.py
bec_ipython_client/plugins/flomni/flomni_config.yaml
tests/conftest.py
tests/client_tests/conftest.py
tests/client_tests/test_beamline_mixins.py
tests/client_tests/test_bec_client.py
tests/client_tests/test_device_progress.py
tests/client_tests/test_ipython_live_updates.py
tests/client_tests/test_live_table.py
tests/client_tests/test_move_callback.py
tests/client_tests/test_pretty_table.py
tests/end-2-end/_ensure_requirements_container.py
tests/end-2-end/test_procedures_e2e.py
tests/end-2-end/test_scans_e2e.py
tests/end-2-end/test_scans_lib_e2e.py
bec_ipython_client-3.94.0.dist-info/METADATA
bec_ipython_client-3.94.0.dist-info/WHEEL
bec_ipython_client-3.94.0.dist-info/entry_points.txt
bec_ipython_client-3.94.0.dist-info/RECORD
